domiknows/__init__.py
domiknows/base.py
domiknows/config.py
domiknows/utils.py
domiknows/compiler/OntologyMLGraph.py
domiknows/compiler/__init__.py
domiknows/compiler/compiler.py
domiknows/data/__init__.py
domiknows/data/reader.py
domiknows/graph/__init__.py
domiknows/graph/base.py
domiknows/graph/candidates.py
domiknows/graph/concept.py
domiknows/graph/dataNode.py
domiknows/graph/dataNodeConfig.py
domiknows/graph/dataNodeDummy.py
domiknows/graph/equality_mixin.py
domiknows/graph/executable.py
domiknows/graph/graph.py
domiknows/graph/logicalConstrain.py
domiknows/graph/property.py
domiknows/graph/relation.py
domiknows/graph/trial.py
domiknows/program/__init__.py
domiknows/program/batchprogram.py
domiknows/program/callbackprogram.py
domiknows/program/loss.py
domiknows/program/lossprogram.py
domiknows/program/metric.py
domiknows/program/model_program.py
domiknows/program/program.py
domiknows/program/tracker.py
domiknows/program/model/__init__.py
domiknows/program/model/base.py
domiknows/program/model/gbi.py
domiknows/program/model/ilpu.py
domiknows/program/model/iml.py
domiknows/program/model/lossModel.py
domiknows/program/model/pytorch.py
domiknows/program/model/torch.py
domiknows/sensor/__init__.py
domiknows/sensor/learner.py
domiknows/sensor/sensor.py
domiknows/sensor/pytorch/__init__.py
domiknows/sensor/pytorch/learnerModels.py
domiknows/sensor/pytorch/learners.py
domiknows/sensor/pytorch/query_sensor.py
domiknows/sensor/pytorch/relation_sensors.py
domiknows/sensor/pytorch/sensors.py
domiknows/sensor/pytorch/utils.py
domiknows/sensor/pytorch/tokenizers/__init__.py
domiknows/sensor/pytorch/tokenizers/spacy.py
domiknows/sensor/pytorch/tokenizers/transformers.py
domiknows/solver/__init__.py
domiknows/solver/dummyILPOntSolver.py
domiknows/solver/gurobiILPBooleanMethods.py
domiknows/solver/gurobiILPOntSolver.py
domiknows/solver/ilpBooleanMethods.py
domiknows/solver/ilpBooleanMethodsCalculator.py
domiknows/solver/ilpConfig.py
domiknows/solver/ilpOntSolver.py
domiknows-1.0.0.dist-info/METADATA
domiknows-1.0.0.dist-info/WHEEL
domiknows-1.0.0.dist-info/top_level.txt
domiknows-1.0.0.dist-info/RECORD
