Metadata-Version: 2.4
Name: domiknows
Version: 1.0.0
Summary: A library provides integration between Domain Knowledge and Deep Learning.
Home-page: https://github.com/HLR/DomiKnowS
Author: Andrzej Uszok, Parisa Kordjamshidi
Author-email: auszok@ihmc.org, kordjams@msu.edu
Requires-Python: >=3.12
Requires-Dist: accelerate>=1.10.1
Requires-Dist: acls==1.0.2
Requires-Dist: dnspython>=2.8.0
Requires-Dist: graphviz>=0.21
Requires-Dist: gurobipy>=12.0.3
Requires-Dist: huggingface-hub>=0.35.0
Requires-Dist: networkx>=3.5
Requires-Dist: nltk>=3.9.1
Requires-Dist: ordered-set>=4.1.0
Requires-Dist: owlready2>=0.48
Requires-Dist: pandas>=2.3.2
Requires-Dist: py7zr>=1.0.0
Requires-Dist: pycocotools>=2.0.10
Requires-Dist: scikit-learn>=1.7.2
Requires-Dist: sentencepiece>=0.2.1
Requires-Dist: setuptools>=80.9.0
Requires-Dist: click>=8.1.0
Requires-Dist: spacy>=3.8.0
Requires-Dist: tokenizers>=0.22.0
Requires-Dist: transformers>=4.56.1
Requires-Dist: colorama
Provides-Extra: dev
Requires-Dist: pytest>=8.3.3; extra == "dev"
Requires-Dist: pytest-cov>=4.0.0; extra == "dev"
Requires-Dist: pytest-xdist>=3.0.0; extra == "dev"
Requires-Dist: flaky>=3.8.0; extra == "dev"
Requires-Dist: black[jupyter]>=24.10.0; extra == "dev"
Requires-Dist: isort>=5.12.0; extra == "dev"
Requires-Dist: mypy>=1.3.0; extra == "dev"
Provides-Extra: cpu
Requires-Dist: torch>=2.7.0; extra == "cpu"
Requires-Dist: torchvision>=0.22.0; extra == "cpu"
Provides-Extra: cu128
Requires-Dist: torch>=2.7.0; extra == "cu128"
Requires-Dist: torchvision>=0.22.0; extra == "cu128"
Provides-Extra: cu126
Requires-Dist: torch>=2.7.0; extra == "cu126"
Requires-Dist: torchvision>=0.22.0; extra == "cu126"
Provides-Extra: xpu
Requires-Dist: torch>=2.7.0; extra == "xpu"
Requires-Dist: torchvision>=0.22.0; extra == "xpu"
Requires-Dist: pytorch-triton-xpu; extra == "xpu"
Dynamic: author
Dynamic: author-email
Dynamic: home-page
